README
setup.py
src/ng_meli/__init__.py
src/ng_meli/ng_meli.py
src/ngmeli.egg-info/PKG-INFO
src/ngmeli.egg-info/SOURCES.txt
src/ngmeli.egg-info/dependency_links.txt
src/ngmeli.egg-info/requires.txt
src/ngmeli.egg-info/top_level.txt