Metadata-Version: 1.1
Name: ngmeli
Version: 0.0.7
Summary: Simple client for MercadoLibre's API.
Home-page: https://github.com/jdsolucoes/Meli
Author: Jefferson Daniel
Author-email: jd.solucoes@gmail.com
License: MIT
Platform: UNKNOWN
Classifier: Development Status :: 2 - Pre-Alpha
Classifier: Intended Audience :: Developers
Classifier: License :: OSI Approved :: MIT License
Classifier: Operating System :: OS Independent
Classifier: Programming Language :: Python
Classifier: Programming Language :: Python :: 2.6
Classifier: Programming Language :: Python :: 2.7
Classifier: Topic :: Software Development :: Libraries :: Python Modules
Classifier: Topic :: Internet
